flask_debugtoolbar_lineprofilerpanel
