Metadata-Version: 1.0
Name: Flask-DebugToolbar-LineProfilerPanel
Version: 1.0.2
Summary: Panel for the Flask Debug toolbar to capture and view line-by-line profiling stats
Home-page: https://github.com/phleet/flask_debugtoolbar_lineprofilerpanel
Author: Jamie Wong
Author-email: jamie.lf.wong@gmail.com
License: MIT
Platform: UNKNOWN
